powergridsim/__init__.py
powergridsim/models_gurobi/__init__.py
powergridsim/models_gurobi/_status_vars_gurobi.py
powergridsim/models_gurobi/_utils_gurobi.py
powergridsim/models_gurobi/generation_limits_gurobi.py
powergridsim/models_gurobi/non_dispatchable_vars_gurobi.py
powergridsim/models_gurobi/objective_gurobi.py
powergridsim/models_gurobi/params_gurobi.py
powergridsim/models_gurobi/power_balance_gurobi.py
powergridsim/models_gurobi/power_vars_gurobi.py
powergridsim/models_gurobi/production_costs_gurobi.py
powergridsim/models_gurobi/ptdf_utils_gurobi.py
powergridsim/models_gurobi/ramping_limits_gurobi.py
powergridsim/models_gurobi/reserve_requirement_gurobi.py
powergridsim/models_gurobi/reserve_vars_gurobi.py
powergridsim/models_gurobi/services_gurobi.py
powergridsim/models_gurobi/startup_costs_gurobi.py
powergridsim/models_gurobi/uptime_downtime_gurobi.py
powergridsim/models_gurobi/transmission_gurobi/__init__.py
powergridsim/models_gurobi/transmission_gurobi/branch.py
powergridsim/models_gurobi/transmission_gurobi/bus.py
powergridsim-1.0.0.dist-info/METADATA
powergridsim-1.0.0.dist-info/WHEEL
powergridsim-1.0.0.dist-info/top_level.txt
powergridsim-1.0.0.dist-info/RECORD
